pybea/__init__.py
pybea/api.py
pybea/pybea.py
pybea-0.7.0a0.dist-info/DESCRIPTION.rst
pybea-0.7.0a0.dist-info/METADATA
pybea-0.7.0a0.dist-info/RECORD
pybea-0.7.0a0.dist-info/WHEEL
pybea-0.7.0a0.dist-info/metadata.json
pybea-0.7.0a0.dist-info/top_level.txt
