Metadata-Version: 1.1
Name: pybea
Version: 0.7.0a0
Summary: Python package for accessing data from the BEA data API
Home-page: https://github.com/davidrpugh/pyBEA
Author: David R. Pugh
Author-email: drpugh@protonmail.com
License: LICENSE.rst
Platform: UNKNOWN
Classifier: Development Status :: 3 - Alpha
Classifier: Intended Audience :: Education
Classifier: Intended Audience :: Science/Research
Classifier: License :: OSI Approved :: MIT License
Classifier: Operating System :: OS Independent
Classifier: Programming Language :: Python
Classifier: Programming Language :: Python :: 3
Classifier: Programming Language :: Python :: 3.6
Classifier: Topic :: Scientific/Engineering
